kens_python_cli/__init__.py
kens_python_cli/main.py
kens_python_cli/models/config.py
kens_python_cli/templates/default/.gitignore
kens_python_cli/templates/default/PROJECT_GUIDE.md
kens_python_cli/templates/default/README.md
kens_python_cli/templates/default/pyproject.toml
kens_python_cli/templates/default/src/{{package_name}}/__init__.py
kens_python_cli/templates/default/src/{{package_name}}/config.py
kens_python_cli/templates/default/src/{{package_name}}/main.py
kens_python_cli/templates/default/src/{{package_name}}/commands/__init__.py
kens_python_cli/templates/default/src/{{package_name}}/commands/info.py
kens_python_cli/templates/default/src/{{package_name}}/commands/process.py
kens_python_cli/templates/default/src/{{package_name}}/utils/__init__.py
kens_python_cli/templates/default/src/{{package_name}}/utils/helpers.py
kens_python_cli/templates/default/src/{{package_name}}/utils/logging.py
kens_python_cli/utils/file_ops.py
kens_python_cli/utils/prompts.py
kens_python_cli-0.1.2.dist-info/METADATA
kens_python_cli-0.1.2.dist-info/WHEEL
kens_python_cli-0.1.2.dist-info/entry_points.txt
kens_python_cli-0.1.2.dist-info/RECORD
