Metadata-Version: 2.4
Name: kens-python-cli
Version: 0.1.2
Summary: Modern Python CLI scaffolding tool for rapid development
Project-URL: Homepage, https://github.com/ken/kens-python-cli
Project-URL: Repository, https://github.com/ken/kens-python-cli
Project-URL: Documentation, https://github.com/ken/kens-python-cli#readme
Project-URL: Issues, https://github.com/ken/kens-python-cli/issues
Author-email: Ken <ken@example.com>
License: MIT
Classifier: Development Status :: 4 - Beta
Classifier: Intended Audience :: Developers
Classifier: License :: OSI Approved :: MIT License
Classifier: Operating System :: OS Independent
Classifier: Programming Language :: Python :: 3
Classifier: Programming Language :: Python :: 3.11
Classifier: Programming Language :: Python :: 3.12
Classifier: Programming Language :: Python :: 3.13
Classifier: Topic :: Software Development :: Code Generators
Classifier: Topic :: Software Development :: Libraries :: Python Modules
Classifier: Topic :: System :: Software Distribution
Requires-Python: >=3.11
Requires-Dist: jinja2>=3.1.0
Requires-Dist: platformdirs>=4.0.0
Requires-Dist: pydantic>=2.5.0
Requires-Dist: rich>=13.0.0
Requires-Dist: tomlkit>=0.12.0
Requires-Dist: typer>=0.12.0
Provides-Extra: dev
Requires-Dist: mypy>=1.7.0; extra == 'dev'
Requires-Dist: pre-commit>=3.0.0; extra == 'dev'
Requires-Dist: pytest-cov>=4.0.0; extra == 'dev'
Requires-Dist: pytest-mock>=3.10.0; extra == 'dev'
Requires-Dist: pytest>=7.0.0; extra == 'dev'
Requires-Dist: ruff>=0.1.0; extra == 'dev'
